{
    "titulo": "Resumo do Documento de Requisitos de Software (DRS)",
    "descricao": "O DRS é fundamental no desenvolvimento de sistemas de software, detalhando funcionalidades, restrições e especificações. Ele serve como guia para a equipe de desenvolvimento e stakeholders, alinhando expectativas e minimizando riscos.",
    "secoes": [
      {
        "titulo": "Importância do Documento de Requisitos",
        "conteudo": [
          "Define o escopo do projeto, evitando ambiguidades.",
          "Atua como meio de comunicação entre a equipe técnica e stakeholders.",
          "Permite estimativas precisas de tempo, recursos e custos.",
          "Serve como referência contínua durante o ciclo de vida do software.",
          "Ajuda a mitigar riscos potenciais."
        ]
      },
      {
        "titulo": "Estrutura do Documento de Requisitos",
        "conteudo": [
          {
            "titulo": "1. Introdução",
            "conteudo": [
              "Objetivo do Documento: Descreve o propósito e o público-alvo do DRS.",
              "Escopo do Sistema: Define o que o sistema fará e não fará.",
              "Definições e Acrônimos: Lista termos técnicos e definições.",
              "Referências: Documentos adicionais utilizados."
            ]
          },
          {
            "titulo": "2. Visão Geral do Sistema",
            "conteudo": [
              "Descrição Geral: Apresenta uma visão de alto nível do sistema.",
              "Diagrama de Arquitetura: Representação visual da estrutura do sistema."
            ]
          },
          {
            "titulo": "3. Requisitos Funcionais",
            "conteudo": [
              "Autenticação de Usuários: Registro e login.",
              "Processamento de Pedidos: Processar pedidos e atualizar status."
            ]
          },
          {
            "titulo": "4. Requisitos Não Funcionais",
            "conteudo": [
              "Desempenho: Processar 100 transações por segundo.",
              "Segurança: Criptografia de dados sensíveis em trânsito e repouso."
            ]
          },
          {
            "titulo": "5. Requisitos de Interface",
            "conteudo": [
              "Interface de Usuário: Descrição das telas.",
              "Interface de API: Especificação de endpoints e formatos de dados."
            ]
          },
          {
            "titulo": "6. Requisitos de Dados",
            "conteudo": [
              "Modelagem de Dados: Diagramas ER ou UML.",
              "Regras de Integridade: Restrições para manter a consistência dos dados."
            ]
          },
          {
            "titulo": "7. Requisitos de Hardware e Software",
            "conteudo": [
              "Plataformas de Desenvolvimento: Linguagens e ferramentas.",
              "Ambientes de Implantação: Servidores e sistemas operacionais."
            ]
          },
          {
            "titulo": "8. Requisitos de Conformidade",
            "conteudo": [
              "Regulamentações de Privacidade: Conformidade com a LGPD.",
              "Padrões de Acessibilidade: Diretrizes WCAG."
            ]
          },
          {
            "titulo": "9. Requisitos de Manutenção e Suporte",
            "conteudo": [
              "Planos de Backup: Estratégias para continuidade do serviço.",
              "Suporte Técnico: Níveis de suporte e tempos de resposta."
            ]
          }
        ]
      },
      {
        "titulo": "Processo de Elaboração do Documento de Requisitos",
        "conteudo": [
          {
            "titulo": "1. Coleta de Requisitos",
            "conteudo": "Identificação das necessidades através de entrevistas e análise de documentos."
          },
          {
            "titulo": "2. Análise de Requisitos",
            "conteudo": "Refinamento dos requisitos coletados."
          },
          {
            "titulo": "3. Documentação",
            "conteudo": "Organização dos requisitos no DRS."
          },
          {
            "titulo": "4. Validação",
            "conteudo": "Revisão dos requisitos com stakeholders."
          },
          {
            "titulo": "5. Gestão de Mudanças",
            "conteudo": "Processo para gerenciar alterações nos requisitos."
          }
        ]
      },
      {
        "titulo": "Ferramentas para Gestão de Requisitos",
        "conteudo": [
          "JIRA: Rastreamento e gerenciamento ágil.",
          "Confluence: Documentação colaborativa.",
          "Microsoft Word ou Google Docs: Criação do DRS.",
          "IBM DOORS: Gestão de requisitos para projetos complexos."
        ]
      },
      {
        "titulo": "Benefícios do Documento de Requisitos",
        "conteudo": [
          "Clareza e Alinhamento: Compreensão comum entre envolvidos.",
          "Redução de Custos e Tempo: Minimiza retrabalhos.",
          "Melhoria na Qualidade do Software: Requisitos claros e testáveis.",
          "Facilitação da Comunicação: Referência central para todas as partes."
        ]
      },
      {
        "titulo": "Desafios na Elaboração do DRS",
        "conteudo": [
          "Ambiguidade nos Requisitos: Pode causar falhas na implementação.",
          "Mudanças Frequentes: Exigem atualizações contínuas.",
          "Engajamento dos Stakeholders: Dificuldades em obter feedback.",
          "Complexidade dos Requisitos: Projetos complexos com interdependências."
        ]
      },
      {
        "titulo": "Boas Práticas na Elaboração do DRS",
        "conteudo": [
          "Clareza e Precisão: Linguagem clara e evitar ambiguidades.",
          "Estruturação Adequada: Organização lógica do documento.",
          "Envolvimento dos Stakeholders: Ativar a participação dos envolvidos.",
          "Revisão Contínua: Realizar revisões periódicas."
        ]
      },
      {
        "titulo": "Conclusão",
        "conteudo": "O DRS é essencial para o sucesso de projetos de software, garantindo alinhamento de expectativas e minimizando riscos."
      }
    ]
  }
  